Workbook

Sheet BOM
A1: Project ROCKY - Pebble (subscale radial pentapod) - Bill of Materials
A2: Prices are July-2026 US estimates (see Source column). Blue cells = edit me (qty, unit price, status). Line totals & rollups are formulas. Already owned (excluded): printer hot ends/nozzles, PLA + CF-PLA + purple PETG stock, Xbox Elite controller.
A4: Phase / Batch | B4: Category | C4: Item | D4: Spec / Notes | E4: Qty | F4: Unit $ (est) | G4: Line Total $ | H4: Source (Jul 2026) | I4: Status
A5: 0-Foundations | B5: Materials | C5: TPU filament 1 kg (95A) | D5: Foot pads, bumpers, gaskets - only filament type not in current stock | E5: 1 | F5: 25 | G5: =E5*F5 -> 25 | H5: Amazon; est | I5: to buy
A6: 0-Foundations | B6: Materials | C6: PETG restock 1 kg x2 | D6: OPTIONAL: when the purple runs out; PLA/CF-PLA cover jigs + Phase-1 links meanwhile | E6: 2 | F6: 20 | G6: =E6*F6 -> 40 | H6: Amazon; est; OPTIONAL | I6: to buy
A7: 0-Foundations | B7: Tools | C7: Digital calipers 150mm | D7: OPTIONAL: skip if owned - essential for CAD fit checks | E7: 1 | F7: 22 | G7: =E7*F7 -> 22 | H7: Amazon; est; OPTIONAL | I7: to buy
A8: 1-One True Leg | B8: Actuators | C8: Feetech/Waveshare ST3215 bus servo, 12V 30kg.cm | D8: MUST be 12V variant; magnetic encoder, 1Mbps TTL bus; $16.99-21.99 depending on vendor | E8: 4 | F8: 19 | G8: =E8*F8 -> 76 | H8: waveshare.com/st3215-servo.htm; Amazon B0CFY52HVV | I8: to buy
A9: 1-One True Leg | B9: Actuators | C9: Feetech SCS0009 micro bus servo | D9: Hand/claw drive prototype; same TTL bus, 2.3 kg.cm | E9: 1 | F9: 12 | G9: =E9*F9 -> 12 | H9: Seeed SCS0009 p-6535; Amazon 2-pack; est | I9: to buy
A10: 1-One True Leg | B10: Electronics | C10: Waveshare Bus Servo Adapter (A) | D10: UART<->TTL bus + servo power distribution | E10: 1 | F10: 7 | G10: =E10*F10 -> 7 | H10: waveshare.com/bus-servo-adapter-a.htm; est | I10: to buy
A11: 1-One True Leg | B11: Electronics | C11: Bench PSU 12V 10A | D11: Powers leg jig before batteries exist; reused as charger supply | E11: 1 | F11: 26 | G11: =E11*F11 -> 26 | H11: Amazon; est | I11: to buy
A12: 1-One True Leg | B12: Mechanical | C12: Compression/die spring assortment | D12: SEA shin: ~7mm travel at 8-12N preload | E12: 1 | F12: 10 | G12: =E12*F12 -> 10 | H12: Amazon/AliExpress; est | I12: to buy
A13: 1-One True Leg | B13: Mechanical | C13: Carbon fiber tube 8-10mm OD x2 | D13: Tibia shins | E13: 2 | F13: 7 | G13: =E13*F13 -> 14 | H13: Amazon/AliExpress; est | I13: to buy
A14: 1-One True Leg | B14: Hardware | C14: M2/M2.5/M3 screw + nut assortment | D14: Mostly M3; includes locknuts | E14: 1 | F14: 25 | G14: =E14*F14 -> 25 | H14: Amazon; est | I14: to buy
A15: 1-One True Leg | B15: Hardware | C15: 683ZZ bearings 3x7x3 (10-pack) | D15: Coxa yaw shaft support | E15: 1 | F15: 8 | G15: =E15*F15 -> 8 | H15: Amazon; est | I15: to buy
A16: 1-One True Leg | B16: Hardware | C16: M3 heat-set inserts (100) | D16: For parts opened repeatedly | E16: 1 | F16: 12 | G16: =E16*F16 -> 12 | H16: Amazon; est | I16: to buy
... A35: 4-Pebble Thinks | B35: Audio | C35: USB mini microphone | D35: Voice commands (or use laptop mic) | E35: 1 | F35: 15 | G35: =E35*F35 -> 15 | H35: Amazon; est | I35: to buy
F37: GRAND TOTAL (all items): | G37: =SUM(G5:G35) -> 1275.95

Sheet Summary
A1: Project ROCKY - Budget Summary
A2: Rolls up live from the BOM sheet via SUMIFS - edit quantities/prices there.
A4: Phase / Batch | B4: Gate (what must work before next spend) | C4: Subtotal $ | D4: Cumulative $
A5: 0-Foundations | B5: Prusa prints PETG cleanly; pentapod walks in MuJoCo sim | C5: =SUMIFS(BOM!$G$5:$G$35,BOM!$A$5:$A$35,A5) -> 87 | D5: =SUM($C$5:C5) -> 87
A6: 1-One True Leg | B6: Bench leg tracks ROS 2 trajectories; SEA shin survives impacts; claw prototype works | C6: =SUMIFS(BOM!$G$5:$G$35,BOM!$A$5:$A$35,A6) -> 208 | D6: =SUM($C$5:C6) -> 295
A7: 2-Pebble Walks | B7: Stands, wave-gait walks omnidirectionally, teleop | C7: =SUMIFS(BOM!$G$5:$G$35,BOM!$A$5:$A$35,A7) -> 639 | D7: =SUM($C$5:C7) -> 934
A8: 3-Pebble Senses | B8: IMU-stabilized body; terrain adaptation via foot contacts; camera streams | C8: =SUMIFS(BOM!$G$5:$G$35,BOM!$A$5:$A$35,A8) -> 312.95 | D8: =SUM($C$5:C8) -> 1246.95
A9: 4-Pebble Thinks | B9: Laptop VLM agent drives robot skills by voice/vision; chord-speak | C9: =SUMIFS(BOM!$G$5:$G$35,BOM!$A$5:$A$35,A9) -> 29 | D9: =SUM($C$5:C9) -> 1275.95
A10: TOTAL | C10: =SUM(C5:C9) -> 1275.95
A12: Budget envelope | B12: 1500
A13: Headroom remaining | B13: =B12-C10 -> 224.05
A15: Trim levers if needed:
A16: Buy ST3215 direct from Waveshare (~$17) or AliExpress official FEETECH store (~$14-16): saves $30-80 across 17 units - VERIFY 12V/30kg.cm variant
A17: Skip the 2 spare servos initially: -$38 (riskier)
A18: Defer OAK-D Lite and lidar (yellow OPTIONAL rows): -$227; or eBay a used robot-vacuum lidar (~$15-30) for Phase 3
A19: One LiPo instead of two to start: -$37
A20: Per-leg marginal cost after leg #1: ~ $70-75 (3x ST3215 + 1x SCS0009); everything else in Batch 1 is one-time shared kit
A22: Legend: blue = editable input (qty, unit price, status, envelope); black = formula; yellow rows on BOM = optional items.
